sqbrite/__init__.py
sqbrite/constants.py
sqbrite/db.py
sqbrite/field.py
sqbrite/heuristics.py
sqbrite/pages.py
sqbrite/record.py
sqbrite/sqlite_recover.py
sqbrite/table.py
sqbrite/tuples.py
sqbrite/utils.py
sqbrite/magic/sqbrite.yaml
sqbrite-0.17.dist-info/LICENSE
sqbrite-0.17.dist-info/METADATA
sqbrite-0.17.dist-info/WHEEL
sqbrite-0.17.dist-info/entry_points.txt
sqbrite-0.17.dist-info/top_level.txt
sqbrite-0.17.dist-info/RECORD
