Metadata-Version: 2.1
Name: sqbrite
Version: 0.17
Summary: SQBrite is a data recovery tool for SQLite databases
Home-page: https://github.com/mattboyer/sqbrite
Author: Matt Boyer
Author-email: mboyer@sdf.org
License: UNKNOWN
Platform: UNKNOWN
Classifier: Development Status :: 2 - Pre-Alpha
Classifier: Intended Audience :: Science/Research
Classifier: License :: OSI Approved :: MIT License
Classifier: Programming Language :: Python :: 3.5
Classifier: Programming Language :: Python :: 3.6
Classifier: Programming Language :: Python :: 3.7
Classifier: Programming Language :: Python :: 3.8
Classifier: Programming Language :: Python :: 3.9
Classifier: Programming Language :: Python :: 3.10
Classifier: Topic :: Database
Classifier: Topic :: System :: Recovery Tools
License-File: LICENSE
Requires-Dist: pyxdg
Requires-Dist: pyyaml
